{"title":"MotoGP.2008.G.P.Australia.-.125.250.MotoGP.PDTV.XviD-Regenzy","uid":4429824,"size":1177726976,"categoryP":"video","categoryS":"tv_shows","magnet":"?xt=urn:btih:070ed235fa20d8e4afac8099305cc340e27fba8e&amp;dn=MotoGP.2008.G.P.Australia.-.125.250.MotoGP.PDTV.XviD-Regenzy&amp;tr=udp%3A%2F%2Ftracker.openbittorrent.com%3A80&amp;tr=udp%3A%2F%2Fopen.demonii.com%3A1337&amp;tr=udp%3A%2F%2Ftracker.coppersurfer.tk%3A6969&amp;tr=udp%3A%2F%2Fexodus.desync.com%3A6969","seeders":0,"leechers":0,"uploader":"Regenzy1","files":3,"time":1223227429,"description":"MotoGP 2008 Gran Premio De Australia (Spanish)\n\nMotoGp 250cc y 125cc ","torrent":{"xt":"urn:btih:070ed235fa20d8e4afac8099305cc340e27fba8e","amp;dn":"MotoGP.2008.G.P.Australia.-.125.250.MotoGP.PDTV.XviD-Regenzy","amp;tr":["udp%3A%2F%2Ftracker.openbittorrent.com%3A80","udp%3A%2F%2Fopen.demonii.com%3A1337","udp%3A%2F%2Ftracker.coppersurfer.tk%3A6969","udp%3A%2F%2Fexodus.desync.com%3A6969"],"infoHash":"070ed235fa20d8e4afac8099305cc340e27fba8e","infoHashBuffer":{"type":"Buffer","data":[7,14,210,53,250,32,216,228,175,172,128,153,48,92,195,64,226,127,186,142]},"announce":[],"urlList":[]}}