{"title":"Yes Man [Rip] - tcaruth","uid":4848386,"size":1056440461,"categoryP":"video","categoryS":"movies","magnet":"?xt=urn:btih:0bded6c28cd94241a10e67fc66251d5408ef9bb5&amp;dn=Yes+Man+%5BRip%5D+-+tcaruth&amp;tr=udp%3A%2F%2Ftracker.openbittorrent.com%3A80&amp;tr=udp%3A%2F%2Fopen.demonii.com%3A1337&amp;tr=udp%3A%2F%2Ftracker.coppersurfer.tk%3A6969&amp;tr=udp%3A%2F%2Fexodus.desync.com%3A6969","seeders":0,"leechers":1,"uploader":"tcaruth","files":3,"time":1239778801,"description":" &lt;a href=&quot;http://www.imdb.com/title/tt1068680/&quot; rel=&quot;nofollow&quot; target=&quot;_NEW&quot;&gt;http://www.imdb.com/title/tt1068680/&lt;/a&gt;\n\n\nCarl Allen is at a standstill. No future... Until the day he enrolls into a personal development program based on a very simple idea: say yes to everything! Carl discovers with amazement the magical power of &quot;Yes&quot;, and sees his professional and romantic life turned upside down overnight: an unexpected promotion and a new girlfriend. But he'll soon discover that better can be good's enemy, and that all opportunities shouldn't be taken.\n\n[2008]","torrent":{"xt":"urn:btih:0bded6c28cd94241a10e67fc66251d5408ef9bb5","amp;dn":"Yes+Man+%5BRip%5D+-+tcaruth","amp;tr":["udp%3A%2F%2Ftracker.openbittorrent.com%3A80","udp%3A%2F%2Fopen.demonii.com%3A1337","udp%3A%2F%2Ftracker.coppersurfer.tk%3A6969","udp%3A%2F%2Fexodus.desync.com%3A6969"],"infoHash":"0bded6c28cd94241a10e67fc66251d5408ef9bb5","infoHashBuffer":{"type":"Buffer","data":[11,222,214,194,140,217,66,65,161,14,103,252,102,37,29,84,8,239,155,181]},"announce":[],"urlList":[]}}