{"title":"[BigTitsAtSchool] Tiffany Tyler (Slutty Seconds / 01.15.2013)","uid":8022269,"size":265837573,"categoryP":"porn","categoryS":"movies","magnet":"?xt=urn:btih:18b3558135c5995d8d600d78c181a3fd3c26aa12&amp;dn=%5BBigTitsAtSchool%5D+Tiffany+Tyler+%28Slutty+Seconds+%2F+01.15.2013%29&amp;tr=udp%3A%2F%2Ftracker.openbittorrent.com%3A80&amp;tr=udp%3A%2F%2Fopen.demonii.com%3A1337&amp;tr=udp%3A%2F%2Ftracker.coppersurfer.tk%3A6969&amp;tr=udp%3A%2F%2Fexodus.desync.com%3A6969","seeders":1,"leechers":1,"uploader":"chkm8te","files":1,"time":1358229869,"description":"[BigTitsAtSchool] Tiffany Tyler (Slutty Seconds / 01.15.2013)\n\nTiffany is very pissed off at her cheating boyfriend, and she's sworn to pay that bastard back. When she shows up at school\ndressed as slutty as can be, she confronts her scumbag boyfriend and threatens to fuck the next person she sees. Enter Johnny...\n\nScreens: &lt;a href=&quot;\nhttp://xxxhost.me/viewer.php?file=eaop4vtry1ukde4h2qer.jpg&quot; rel=&quot;nofollow&quot; target=&quot;_NEW&quot;&gt;\nhttp://xxxhost.me/viewer.php?file=eaop4vtry1ukde4h2qer.jpg&lt;/a&gt;\n &lt;a href=&quot;\nhttp://xxxhost.me/viewer.php?file=ukxoztmdq7fn69l8ois4.jpg&quot; rel=&quot;nofollow&quot; target=&quot;_NEW&quot;&gt;\nhttp://xxxhost.me/viewer.php?file=ukxoztmdq7fn69l8ois4.jpg&lt;/a&gt;","torrent":{"xt":"urn:btih:18b3558135c5995d8d600d78c181a3fd3c26aa12","amp;dn":"%5BBigTitsAtSchool%5D+Tiffany+Tyler+%28Slutty+Seconds+%2F+01.15.2013%29","amp;tr":["udp%3A%2F%2Ftracker.openbittorrent.com%3A80","udp%3A%2F%2Fopen.demonii.com%3A1337","udp%3A%2F%2Ftracker.coppersurfer.tk%3A6969","udp%3A%2F%2Fexodus.desync.com%3A6969"],"infoHash":"18b3558135c5995d8d600d78c181a3fd3c26aa12","infoHashBuffer":{"type":"Buffer","data":[24,179,85,129,53,197,153,93,141,96,13,120,193,129,163,253,60,38,170,18]},"announce":[],"urlList":[]}}