{"title":"Trance In Motion Vol. 41 (2010).","uid":5354497,"size":140659470,"categoryP":"audio","categoryS":"music","magnet":"?xt=urn:btih:198beedf9482547675cd0752a5fa91dd68865666&amp;dn=Trance+In+Motion+Vol.+41+%282010%29.&amp;tr=udp%3A%2F%2Ftracker.openbittorrent.com%3A80&amp;tr=udp%3A%2F%2Fopen.demonii.com%3A1337&amp;tr=udp%3A%2F%2Ftracker.coppersurfer.tk%3A6969&amp;tr=udp%3A%2F%2Fexodus.desync.com%3A6969","seeders":0,"leechers":1,"uploader":"zurera","files":1,"time":1265848652,"description":"135 MB | Trance | 320 Kbps | \n\n\n\n01.Ashley Wallbridge - Melodies (Intro Edit)\n02.Moonbeam &amp; Tyler Michaud feat. Tiff lacey - Openhearted (Swen Weber Remix)\n03.Arnej - They Need Us (Original Mix)\n04.Estiva &amp; Temple One - November Lonely (Estiva Mix)\n05.Tucandeo - Blue Shores (Original Mix)\n06.Luca De Maas feat. La'Cor - Never Ending Misery (Octava Electronica Remix)\n07.EnMass feat. Cari Golden - So Please 2010 (Randy Boyer Mix)\n08.Tritonal feat. Soto - One More Day (Original Mix)\n09.M6 &amp; Klauss Goulart - Hidden Light (Original Mix)\n10.Mark Sinclair - Pictures Of You (Terry ferminal Mix)","torrent":{"xt":"urn:btih:198beedf9482547675cd0752a5fa91dd68865666","amp;dn":"Trance+In+Motion+Vol.+41+%282010%29.","amp;tr":["udp%3A%2F%2Ftracker.openbittorrent.com%3A80","udp%3A%2F%2Fopen.demonii.com%3A1337","udp%3A%2F%2Ftracker.coppersurfer.tk%3A6969","udp%3A%2F%2Fexodus.desync.com%3A6969"],"infoHash":"198beedf9482547675cd0752a5fa91dd68865666","infoHashBuffer":{"type":"Buffer","data":[25,139,238,223,148,130,84,118,117,205,7,82,165,250,145,221,104,134,86,102]},"announce":[],"urlList":[]}}