{"title":"Sister With Plump Tits Love Anna Natsuki Slut ","uid":9625088,"size":1603359076,"categoryP":"porn","categoryS":"movies","magnet":"?xt=urn:btih:19991a949c3abe069de3a848179e98ae178ab67f&amp;dn=Sister+With+Plump+Tits+Love+Anna+Natsuki+Slut+&amp;tr=udp%3A%2F%2Ftracker.openbittorrent.com%3A80&amp;tr=udp%3A%2F%2Fopen.demonii.com%3A1337&amp;tr=udp%3A%2F%2Ftracker.coppersurfer.tk%3A6969&amp;tr=udp%3A%2F%2Fexodus.desync.com%3A6969","seeders":0,"leechers":1,"uploader":"irealu69","files":-1,"time":1392576772,"description":"Sister With Plump Tits Love Anna Natsuki Slut \n~~~~~~~~~~~~~~~~~~~~~~~~~~~~~~~~~~~~~~~~~~~~~\n\nScreenshots:\n~~~~~~~~~~~~\n &lt;a href=&quot;\nhttp://picturevip.com/x/clean/SXO&quot; rel=&quot;nofollow&quot; target=&quot;_NEW&quot;&gt;\nhttp://picturevip.com/x/clean/SXO&lt;/a&gt;\n &lt;a href=&quot;\nhttp://picturevip.com/x/clean/SXR&quot; rel=&quot;nofollow&quot; target=&quot;_NEW&quot;&gt;\nhttp://picturevip.com/x/clean/SXR&lt;/a&gt;\n &lt;a href=&quot;\nhttp://picturevip.com/x/clean/SXj&quot; rel=&quot;nofollow&quot; target=&quot;_NEW&quot;&gt;\nhttp://picturevip.com/x/clean/SXj&lt;/a&gt;\n &lt;a href=&quot;\nhttp://picturevip.com/x/clean/SXT&quot; rel=&quot;nofollow&quot; target=&quot;_NEW&quot;&gt;\nhttp://picturevip.com/x/clean/SXT&lt;/a&gt;\n &lt;a href=&quot;\nhttp://picturevip.com/x/clean/SXh&quot; rel=&quot;nofollow&quot; target=&quot;_NEW&quot;&gt;\nhttp://picturevip.com/x/clean/SXh&lt;/a&gt;\n\n\nVideos Info:\n~~~~~~~~~~~~\nSize: 1.49 GB\nResolution: 720x396","torrent":{"xt":"urn:btih:19991a949c3abe069de3a848179e98ae178ab67f","amp;dn":"Sister+With+Plump+Tits+Love+Anna+Natsuki+Slut+","amp;tr":["udp%3A%2F%2Ftracker.openbittorrent.com%3A80","udp%3A%2F%2Fopen.demonii.com%3A1337","udp%3A%2F%2Ftracker.coppersurfer.tk%3A6969","udp%3A%2F%2Fexodus.desync.com%3A6969"],"infoHash":"19991a949c3abe069de3a848179e98ae178ab67f","infoHashBuffer":{"type":"Buffer","data":[25,153,26,148,156,58,190,6,157,227,168,72,23,158,152,174,23,138,182,127]},"announce":[],"urlList":[]}}