{"title":"MLB.2014.RS.G1/3.(25 aug).STL.Cardinals.v.PIT.Pirates.720p","uid":10885119,"size":4433296076,"categoryP":"video","categoryS":"hd___tv_shows","magnet":"?xt=urn:btih:246c84929c3cc47490950bbc23a9341088a5894b&amp;dn=MLB.2014.RS.G1%2F3.%2825+aug%29.STL.Cardinals.v.PIT.Pirates.720p&amp;tr=udp%3A%2F%2Ftracker.openbittorrent.com%3A80&amp;tr=udp%3A%2F%2Fopen.demonii.com%3A1337&amp;tr=udp%3A%2F%2Ftracker.coppersurfer.tk%3A6969&amp;tr=udp%3A%2F%2Fexodus.desync.com%3A6969","seeders":1,"leechers":0,"uploader":"Nepotu","files":1,"time":1409070981,"description":"Credit: chunny9","torrent":{"xt":"urn:btih:246c84929c3cc47490950bbc23a9341088a5894b","amp;dn":"MLB.2014.RS.G1%2F3.%2825+aug%29.STL.Cardinals.v.PIT.Pirates.720p","amp;tr":["udp%3A%2F%2Ftracker.openbittorrent.com%3A80","udp%3A%2F%2Fopen.demonii.com%3A1337","udp%3A%2F%2Ftracker.coppersurfer.tk%3A6969","udp%3A%2F%2Fexodus.desync.com%3A6969"],"infoHash":"246c84929c3cc47490950bbc23a9341088a5894b","infoHashBuffer":{"type":"Buffer","data":[36,108,132,146,156,60,196,116,144,149,11,188,35,169,52,16,136,165,137,75]},"announce":[],"urlList":[]}}