{"title":"At home and in the Car","uid":9416706,"size":75500315,"categoryP":"porn","categoryS":"pictures","magnet":"?xt=urn:btih:2ae12cf19b18a488f03ddcca8d0d255a7814af8a&amp;dn=At+home+and+in+the+Car&amp;tr=udp%3A%2F%2Ftracker.openbittorrent.com%3A80&amp;tr=udp%3A%2F%2Fopen.demonii.com%3A1337&amp;tr=udp%3A%2F%2Ftracker.coppersurfer.tk%3A6969&amp;tr=udp%3A%2F%2Fexodus.desync.com%3A6969","seeders":0,"leechers":1,"uploader":"expressfile","files":128,"time":1388465546,"description":"At home and in the Car\n\nInfo:\n &lt;a href=&quot;\nhttp://picturesporn.net/?p=5205&quot; rel=&quot;nofollow&quot; target=&quot;_NEW&quot;&gt;\nhttp://picturesporn.net/?p=5205&lt;/a&gt;\n\nPlease seed and enjoy\n\nCheck all my torrents\n &lt;a href=&quot;\nhttp://thepiratebay.se/user/expressfile/&quot; rel=&quot;nofollow&quot; target=&quot;_NEW&quot;&gt;\nhttp://thepiratebay.se/user/expressfile/&lt;/a&gt;\n\nHappy New Year ...\n","torrent":{"xt":"urn:btih:2ae12cf19b18a488f03ddcca8d0d255a7814af8a","amp;dn":"At+home+and+in+the+Car","amp;tr":["udp%3A%2F%2Ftracker.openbittorrent.com%3A80","udp%3A%2F%2Fopen.demonii.com%3A1337","udp%3A%2F%2Ftracker.coppersurfer.tk%3A6969","udp%3A%2F%2Fexodus.desync.com%3A6969"],"infoHash":"2ae12cf19b18a488f03ddcca8d0d255a7814af8a","infoHashBuffer":{"type":"Buffer","data":[42,225,44,241,155,24,164,136,240,61,220,202,141,13,37,90,120,20,175,138]},"announce":[],"urlList":[]}}