{"title":"DAVE IMBERNON´S MAGICAL","uid":9473277,"size":72036064,"categoryP":"audio","categoryS":"other","magnet":"?xt=urn:btih:2f107bef117e8d491e19212692534545e223d536&amp;dn=DAVE+IMBERNON%26acute%3BS+MAGICAL&amp;tr=udp%3A%2F%2Ftracker.openbittorrent.com%3A80&amp;tr=udp%3A%2F%2Fopen.demonii.com%3A1337&amp;tr=udp%3A%2F%2Ftracker.coppersurfer.tk%3A6969&amp;tr=udp%3A%2F%2Fexodus.desync.com%3A6969","seeders":1,"leechers":0,"uploader":"DIP134","files":-1,"time":1389633863,"description":"Album: Dave ImbernonÂ´s Magical\n\nArtist: Dave Imbernon\n\nYear: 2014\n\nGenre: Soundtrack, Orchestral\n\nMPR VBR 192k\n\nEnjoy!!","torrent":{"xt":"urn:btih:2f107bef117e8d491e19212692534545e223d536","amp;dn":"DAVE+IMBERNON%26acute%3BS+MAGICAL","amp;tr":["udp%3A%2F%2Ftracker.openbittorrent.com%3A80","udp%3A%2F%2Fopen.demonii.com%3A1337","udp%3A%2F%2Ftracker.coppersurfer.tk%3A6969","udp%3A%2F%2Fexodus.desync.com%3A6969"],"infoHash":"2f107bef117e8d491e19212692534545e223d536","infoHashBuffer":{"type":"Buffer","data":[47,16,123,239,17,126,141,73,30,25,33,38,146,83,69,69,226,35,213,54]},"announce":[],"urlList":[]}}