{"title":"All American Rejects- Beekeepers Daughter 720p DL","uid":7075836,"size":81114684,"categoryP":"video","categoryS":"music_videos","magnet":"?xt=urn:btih:3874990c284901c18ebb29a7ac2b210ea642fd08&amp;dn=All+American+Rejects-+Beekeepers+Daughter+720p+DL&amp;tr=udp%3A%2F%2Ftracker.openbittorrent.com%3A80&amp;tr=udp%3A%2F%2Fopen.demonii.com%3A1337&amp;tr=udp%3A%2F%2Ftracker.coppersurfer.tk%3A6969&amp;tr=udp%3A%2F%2Fexodus.desync.com%3A6969","seeders":1,"leechers":0,"uploader":"dylanlutchman","files":1,"time":1330833819,"description":"All American Rejects - Beekeeper's Daughter\n\nHeight/Width         - 1280*720\n\nYear                 - 2012\n\nSize                 - 77.3mb\n\nFormat               - mp4\n\nLength               - 3:42\n\n\n\n\nKeep seeding and please comment\n\nBe sure to check out my other kool music videos","torrent":{"xt":"urn:btih:3874990c284901c18ebb29a7ac2b210ea642fd08","amp;dn":"All+American+Rejects-+Beekeepers+Daughter+720p+DL","amp;tr":["udp%3A%2F%2Ftracker.openbittorrent.com%3A80","udp%3A%2F%2Fopen.demonii.com%3A1337","udp%3A%2F%2Ftracker.coppersurfer.tk%3A6969","udp%3A%2F%2Fexodus.desync.com%3A6969"],"infoHash":"3874990c284901c18ebb29a7ac2b210ea642fd08","infoHashBuffer":{"type":"Buffer","data":[56,116,153,12,40,73,1,193,142,187,41,167,172,43,33,14,166,66,253,8]},"announce":[],"urlList":[]}}