{"title":"1986 - Uzeb &amp; Didier Lockwood - Absolutely Live [256k]","uid":3747072,"size":68587372,"categoryP":"audio","categoryS":"music","magnet":"?xt=urn:btih:446df2f61153e0ff7320234e7554afccf900c5c0&amp;dn=1986+-+Uzeb+%26+Didier+Lockwood+-+Absolutely+Live+%5B256k%5D&amp;tr=udp%3A%2F%2Ftracker.openbittorrent.com%3A80&amp;tr=udp%3A%2F%2Fopen.demonii.com%3A1337&amp;tr=udp%3A%2F%2Ftracker.coppersurfer.tk%3A6969&amp;tr=udp%3A%2F%2Fexodus.desync.com%3A6969","seeders":0,"leechers":5,"uploader":"ongaswie","files":6,"time":1184880493,"description":"Canadian jazzrock trio Uzeb live on stage with Didier Lockwood. Enjoy!","torrent":{"xt":"urn:btih:446df2f61153e0ff7320234e7554afccf900c5c0","amp;dn":"1986+-+Uzeb+%26+Didier+Lockwood+-+Absolutely+Live+%5B256k%5D","amp;tr":["udp%3A%2F%2Ftracker.openbittorrent.com%3A80","udp%3A%2F%2Fopen.demonii.com%3A1337","udp%3A%2F%2Ftracker.coppersurfer.tk%3A6969","udp%3A%2F%2Fexodus.desync.com%3A6969"],"infoHash":"446df2f61153e0ff7320234e7554afccf900c5c0","infoHashBuffer":{"type":"Buffer","data":[68,109,242,246,17,83,224,255,115,32,35,78,117,84,175,204,249,0,197,192]},"announce":[],"urlList":[]}}