{"title":"Nip.Tuck.S01.SWESUB.HDTV.XviD-Exitoz","uid":7055359,"size":4923930624,"categoryP":"video","categoryS":"tv_shows","magnet":"?xt=urn:btih:496d317776f674360593bd97c7f6f62ee29fd305&amp;dn=Nip.Tuck.S01.SWESUB.HDTV.XviD-Exitoz&amp;tr=udp%3A%2F%2Ftracker.openbittorrent.com%3A80&amp;tr=udp%3A%2F%2Fopen.demonii.com%3A1337&amp;tr=udp%3A%2F%2Ftracker.coppersurfer.tk%3A6969&amp;tr=udp%3A%2F%2Fexodus.desync.com%3A6969","seeders":1,"leechers":0,"uploader":"Exiitoz","files":13,"time":1330089313,"description":"SkÃƒÂ¶nhet kommer inifrÃƒÂ¥n brukar det sÃƒÂ¤gas. Men pÃƒÂ¥ plastikkirurgikliniken i Miami i South Beach som drivs av Sean McNamara och Christian Troy, kommer skÃƒÂ¶nheten frÃƒÂ¥n utsidan.\n\nKirurgerna sjÃƒÂ¤lva tampas med karriÃƒÂ¤ren, livskriser och familjeproblem. Nip/Tuck ÃƒÂ¤r en serie fylld av intriger, sex och inte minst satir.","torrent":{"xt":"urn:btih:496d317776f674360593bd97c7f6f62ee29fd305","amp;dn":"Nip.Tuck.S01.SWESUB.HDTV.XviD-Exitoz","amp;tr":["udp%3A%2F%2Ftracker.openbittorrent.com%3A80","udp%3A%2F%2Fopen.demonii.com%3A1337","udp%3A%2F%2Ftracker.coppersurfer.tk%3A6969","udp%3A%2F%2Fexodus.desync.com%3A6969"],"infoHash":"496d317776f674360593bd97c7f6f62ee29fd305","infoHashBuffer":{"type":"Buffer","data":[73,109,49,119,118,246,116,54,5,147,189,151,199,246,246,46,226,159,211,5]},"announce":[],"urlList":[]}}