{"title":"BID-051 Hosaka Eri, Suzumura iroha, Arisawa Risa JAV CENSORED","uid":10268673,"size":1656598241,"categoryP":"porn","categoryS":"movie_clips","magnet":"?xt=urn:btih:5ebff96d23ac0624ec58bf822f7dd888190d11d2&amp;dn=BID-051+Hosaka+Eri%2C+Suzumura+iroha%2C+Arisawa+Risa+JAV+CENSORED&amp;tr=udp%3A%2F%2Ftracker.openbittorrent.com%3A80&amp;tr=udp%3A%2F%2Fopen.demonii.com%3A1337&amp;tr=udp%3A%2F%2Ftracker.coppersurfer.tk%3A6969&amp;tr=udp%3A%2F%2Fexodus.desync.com%3A6969","seeders":0,"leechers":9,"uploader":"3xplanet","files":1,"time":1401549585,"description":"BID-051 Hosaka Eri, Suzumura iroha, Arisawa Risa JAV CENSORED\nCover &lt;a href=&quot;\nhttp://www.3xplanet.com/view/42866.html&quot; rel=&quot;nofollow&quot; target=&quot;_NEW&quot;&gt;\nhttp://www.3xplanet.com/view/42866.html&lt;/a&gt;\nScreenshot &lt;a href=&quot;\nhttp://www.3xplanet.com/view/42931.html&quot; rel=&quot;nofollow&quot; target=&quot;_NEW&quot;&gt;\nhttp://www.3xplanet.com/view/42931.html&lt;/a&gt;\nTitle: \nStarring: Hosaka Eri, Suzumura iroha, Arisawa Risa\nStudio:  beauty\n\nTag: JAV, CENSORED, beauty, slut, Big tits\n\n","torrent":{"xt":"urn:btih:5ebff96d23ac0624ec58bf822f7dd888190d11d2","amp;dn":"BID-051+Hosaka+Eri%2C+Suzumura+iroha%2C+Arisawa+Risa+JAV+CENSORED","amp;tr":["udp%3A%2F%2Ftracker.openbittorrent.com%3A80","udp%3A%2F%2Fopen.demonii.com%3A1337","udp%3A%2F%2Ftracker.coppersurfer.tk%3A6969","udp%3A%2F%2Fexodus.desync.com%3A6969"],"infoHash":"5ebff96d23ac0624ec58bf822f7dd888190d11d2","infoHashBuffer":{"type":"Buffer","data":[94,191,249,109,35,172,6,36,236,88,191,130,47,125,216,136,25,13,17,210]},"announce":[],"urlList":[]}}