{"title":"Black Hole Rady 2013 (320kbps) (AciDToX8)","uid":8537340,"size":156604635,"categoryP":"audio","categoryS":"music","magnet":"?xt=urn:btih:62a8c34446ab899d2c86468e3f3dff45beae814d&amp;dn=Black+Hole+Rady+2013+%28320kbps%29+%28AciDToX8%29&amp;tr=udp%3A%2F%2Ftracker.openbittorrent.com%3A80&amp;tr=udp%3A%2F%2Fopen.demonii.com%3A1337&amp;tr=udp%3A%2F%2Ftracker.coppersurfer.tk%3A6969&amp;tr=udp%3A%2F%2Fexodus.desync.com%3A6969","seeders":1,"leechers":0,"uploader":"TranceMedic","files":-1,"time":1370293254,"description":"                           Black Hole Radio May 2013  \n\n                              Trance | Black Hole \n\n           320 kbps | MP3 | unmixed | 2013-06-03 | 01:04:57 | 149 Mb\n\n\n\n\nTracklist:\n\n\n\n01. Freestylers &amp; Stereo Type ft Takura - The Coming Storm (Radio Edit)\n \n02. Giuseppe Ottaviani &amp; Eric Lumiere - Love Will Bring It All Around (Radio Edit)\n\n03. Richard Durand - Radical (Radio Edit)\n\n04. Solarstone - Please (Radio Edit)\n\n05. Andy Duguid &amp; Julie Thompson - Skin &amp; Bones (Radio Edit)\n\n06. Steve Kaetzel ft Brianna Holan - Darling (Radio Edit)\n\n07. Mark Norman ft Mike Schmid - Locked Inside (Radio Edit)\n\n08. Johan Gielen vs Virtual Vault - Intensive (Radio Edit)\n\n09. Bobina - Basque the Dog (Radio Edit)\n\n10. Eddie Amador, IDeaL, J-Break ft Vanity Police - I Need You (Radio Edit)\n \n11. First State - Humanoid (Original Mix)\n\n12. Damn You Mongolians ft Liyah - Prague\n\n13. Thomas Penton &amp; Re-Zone - Back In Time\n\n14. Andy Leka - Otter\n\n15. Wess ft Jade Ross - Crashing Down (Original Mix)\n\n\n\n\nMake music, not war... Enjoy!\n\n\n","torrent":{"xt":"urn:btih:62a8c34446ab899d2c86468e3f3dff45beae814d","amp;dn":"Black+Hole+Rady+2013+%28320kbps%29+%28AciDToX8%29","amp;tr":["udp%3A%2F%2Ftracker.openbittorrent.com%3A80","udp%3A%2F%2Fopen.demonii.com%3A1337","udp%3A%2F%2Ftracker.coppersurfer.tk%3A6969","udp%3A%2F%2Fexodus.desync.com%3A6969"],"infoHash":"62a8c34446ab899d2c86468e3f3dff45beae814d","infoHashBuffer":{"type":"Buffer","data":[98,168,195,68,70,171,137,157,44,134,70,142,63,61,255,69,190,174,129,77]},"announce":[],"urlList":[]}}