{"title":"Farrah Flower - Big Booty Redhead Gets Fucked HD 720p","uid":11047420,"size":1625586457,"categoryP":"porn","categoryS":"hd___movies","magnet":"?xt=urn:btih:838f663426e38bed280ccab0819d5876273eccfe&amp;dn=Farrah+Flower+-+Big+Booty+Redhead+Gets+Fucked+HD+720p&amp;tr=udp%3A%2F%2Ftracker.openbittorrent.com%3A80&amp;tr=udp%3A%2F%2Fopen.demonii.com%3A1337&amp;tr=udp%3A%2F%2Ftracker.coppersurfer.tk%3A6969&amp;tr=udp%3A%2F%2Fexodus.desync.com%3A6969","seeders":1,"leechers":0,"uploader":"ElitePorn","files":-1,"time":1410969488,"description":"Farrah Flower - Big Booty Redhead Gets Fucked HD 720p\n-----------------------------------------------------\n\nScreenshots:\n------------\n\n &lt;a href=&quot;\nhttp://picturescream.asia/soft/mgo&quot; rel=&quot;nofollow&quot; target=&quot;_NEW&quot;&gt;\nhttp://picturescream.asia/soft/mgo&lt;/a&gt;\n &lt;a href=&quot;\nhttp://picturescream.asia/soft/mgH&quot; rel=&quot;nofollow&quot; target=&quot;_NEW&quot;&gt;\nhttp://picturescream.asia/soft/mgH&lt;/a&gt;\n &lt;a href=&quot;\nhttp://picturescream.asia/soft/mgd&quot; rel=&quot;nofollow&quot; target=&quot;_NEW&quot;&gt;\nhttp://picturescream.asia/soft/mgd&lt;/a&gt;\n &lt;a href=&quot;\nhttp://picturescream.asia/soft/mgB&quot; rel=&quot;nofollow&quot; target=&quot;_NEW&quot;&gt;\nhttp://picturescream.asia/soft/mgB&lt;/a&gt;\n &lt;a href=&quot;\nhttp://picturescream.asia/soft/mgE&quot; rel=&quot;nofollow&quot; target=&quot;_NEW&quot;&gt;\nhttp://picturescream.asia/soft/mgE&lt;/a&gt;\n &lt;a href=&quot;\nhttp://picturescream.asia/soft/mga&quot; rel=&quot;nofollow&quot; target=&quot;_NEW&quot;&gt;\nhttp://picturescream.asia/soft/mga&lt;/a&gt;\n\n\nDuration: 01:10:46, Format: mp4, Resolution: 1280x720, Size: 1.514 GB","torrent":{"xt":"urn:btih:838f663426e38bed280ccab0819d5876273eccfe","amp;dn":"Farrah+Flower+-+Big+Booty+Redhead+Gets+Fucked+HD+720p","amp;tr":["udp%3A%2F%2Ftracker.openbittorrent.com%3A80","udp%3A%2F%2Fopen.demonii.com%3A1337","udp%3A%2F%2Ftracker.coppersurfer.tk%3A6969","udp%3A%2F%2Fexodus.desync.com%3A6969"],"infoHash":"838f663426e38bed280ccab0819d5876273eccfe","infoHashBuffer":{"type":"Buffer","data":[131,143,102,52,38,227,139,237,40,12,202,176,129,157,88,118,39,62,204,254]},"announce":[],"urlList":[]}}