{"title":"The.Tomorrow.People.US.S01E21.HDTV.XviD-AFG","uid":10062590,"size":355166269,"categoryP":"video","categoryS":"tv_shows","magnet":"?xt=urn:btih:8ab3e26ea7ce6afea50721a8c5549b779395c0dc&amp;dn=The.Tomorrow.People.US.S01E21.HDTV.XviD-AFG&amp;tr=udp%3A%2F%2Ftracker.openbittorrent.com%3A80&amp;tr=udp%3A%2F%2Fopen.demonii.com%3A1337&amp;tr=udp%3A%2F%2Ftracker.coppersurfer.tk%3A6969&amp;tr=udp%3A%2F%2Fexodus.desync.com%3A6969","seeders":1,"leechers":0,"uploader":"sceneline","files":4,"time":1398752581,"description":"-\nsignup open at Scenetime !!!\n\nFor the sake of sharing, Please seed as long as you can\n\n\n\n ............ NFO .............\n-\t\nFor more info about this show check NFO file\n-","torrent":{"xt":"urn:btih:8ab3e26ea7ce6afea50721a8c5549b779395c0dc","amp;dn":"The.Tomorrow.People.US.S01E21.HDTV.XviD-AFG","amp;tr":["udp%3A%2F%2Ftracker.openbittorrent.com%3A80","udp%3A%2F%2Fopen.demonii.com%3A1337","udp%3A%2F%2Ftracker.coppersurfer.tk%3A6969","udp%3A%2F%2Fexodus.desync.com%3A6969"],"infoHash":"8ab3e26ea7ce6afea50721a8c5549b779395c0dc","infoHashBuffer":{"type":"Buffer","data":[138,179,226,110,167,206,106,254,165,7,33,168,197,84,155,119,147,149,192,220]},"announce":[],"urlList":[]}}