{"title":"In Time 2011 TS XviD V2 READNFO - MiSTERE","uid":6799869,"size":1489319153,"categoryP":"video","categoryS":"movies","magnet":"?xt=urn:btih:94730fd3d22b93a08b66e7cfc3bc7228d4238b1c&amp;dn=In+Time+2011+TS+XviD+V2+READNFO+-+MiSTERE&amp;tr=udp%3A%2F%2Ftracker.openbittorrent.com%3A80&amp;tr=udp%3A%2F%2Fopen.demonii.com%3A1337&amp;tr=udp%3A%2F%2Ftracker.coppersurfer.tk%3A6969&amp;tr=udp%3A%2F%2Fexodus.desync.com%3A6969","seeders":1,"leechers":0,"uploader":"UltraTorrents","files":3,"time":1320661238,"description":"INFO, POSTER &amp; TRAILER:\n                                      &lt;a href=&quot;\nhttp://www.sharepixon.net/movies/in-time&quot; rel=&quot;nofollow&quot; target=&quot;_NEW&quot;&gt;\nhttp://www.sharepixon.net/movies/in-time&lt;/a&gt;\n\n[url]http://www.sharepixon.net/movies/in-time[/url]\n\t\n\n\nSCREENSHOTS:\n                    &lt;a href=&quot;\nhttp://img.sharepixon.net/?v=intimeefe.png&quot; rel=&quot;nofollow&quot; target=&quot;_NEW&quot;&gt;\nhttp://img.sharepixon.net/?v=intimeefe.png&lt;/a&gt; &lt;a href=&quot;\nhttp://img.sharepixon.net/?v=intimeaia.png&quot; rel=&quot;nofollow&quot; target=&quot;_NEW&quot;&gt;\nhttp://img.sharepixon.net/?v=intimeaia.png&lt;/a&gt;\n\n[url]http://img.sharepixon.net/?v=intimeefe.png[/url]\n[url]http://img.sharepixon.net/?v=intimeaia.png[/url]\n\t\n\t\n\nREADNFO:\n\n'Thanks to RELiZLABS for the source files\nSharpened Resized and tweaked RGB\nVideo missing a few seconds here and there\nbut nothing important\nNew, much better LiNE than V1 \ntake it or leave it'","torrent":{"xt":"urn:btih:94730fd3d22b93a08b66e7cfc3bc7228d4238b1c","amp;dn":"In+Time+2011+TS+XviD+V2+READNFO+-+MiSTERE","amp;tr":["udp%3A%2F%2Ftracker.openbittorrent.com%3A80","udp%3A%2F%2Fopen.demonii.com%3A1337","udp%3A%2F%2Ftracker.coppersurfer.tk%3A6969","udp%3A%2F%2Fexodus.desync.com%3A6969"],"infoHash":"94730fd3d22b93a08b66e7cfc3bc7228d4238b1c","infoHashBuffer":{"type":"Buffer","data":[148,115,15,211,210,43,147,160,139,102,231,207,195,188,114,40,212,35,139,28]},"announce":[],"urlList":[]}}