{"title":"Parche 2.0 RE4","uid":8505852,"size":1497816712,"categoryP":"games","categoryS":"pc","magnet":"?xt=urn:btih:96b1c450d92377ed0ec553b706ecc1850f959e7c&amp;dn=Parche+2.0+RE4&amp;tr=udp%3A%2F%2Ftracker.openbittorrent.com%3A80&amp;tr=udp%3A%2F%2Fopen.demonii.com%3A1337&amp;tr=udp%3A%2F%2Ftracker.coppersurfer.tk%3A6969&amp;tr=udp%3A%2F%2Fexodus.desync.com%3A6969","seeders":1,"leechers":0,"uploader":"alexam488","files":6,"time":1369419182,"description":"Parche 2.0 para resident evil 4 \nmejora la claidad de graficas \nespero que les ayude \nsaludos :)","torrent":{"xt":"urn:btih:96b1c450d92377ed0ec553b706ecc1850f959e7c","amp;dn":"Parche+2.0+RE4","amp;tr":["udp%3A%2F%2Ftracker.openbittorrent.com%3A80","udp%3A%2F%2Fopen.demonii.com%3A1337","udp%3A%2F%2Ftracker.coppersurfer.tk%3A6969","udp%3A%2F%2Fexodus.desync.com%3A6969"],"infoHash":"96b1c450d92377ed0ec553b706ecc1850f959e7c","infoHashBuffer":{"type":"Buffer","data":[150,177,196,80,217,35,119,237,14,197,83,183,6,236,193,133,15,149,158,124]},"announce":[],"urlList":[]}}