{"title":"Golden Dawn - Return to Provenance (2012) [mp3@320]","uid":7043071,"size":90054535,"categoryP":"audio","categoryS":"music","magnet":"?xt=urn:btih:a4bd8dc7ab921c29f502e2e553d89d69aee169a9&amp;dn=Golden+Dawn+-+Return+to+Provenance+%282012%29+%5Bmp3%40320%5D&amp;tr=udp%3A%2F%2Ftracker.openbittorrent.com%3A80&amp;tr=udp%3A%2F%2Fopen.demonii.com%3A1337&amp;tr=udp%3A%2F%2Ftracker.coppersurfer.tk%3A6969&amp;tr=udp%3A%2F%2Fexodus.desync.com%3A6969","seeders":1,"leechers":0,"uploader":"zibbik","files":8,"time":1329620815,"description":"\nGenre: Extreme Gothic Metal\nOrigin: Austria\nFormat: 320 kbps\nTT: 37:30\n\n1. Nameless 04:22\n2. Return to Providence 04:49\n3. Dark Illuminations 04:59\n4. Dionysian Eucharist 04:58\n5. Denial 03:45\n6. Seduction 04:35\n7. Vision of Entirety 04:49\n8. Self-destruction 05:27\n &lt;a href=&quot;\nhttp://www.goldendawn.at/&quot; rel=&quot;nofollow&quot; target=&quot;_NEW&quot;&gt;\nhttp://www.goldendawn.at/&lt;/a&gt;\n\n","torrent":{"xt":"urn:btih:a4bd8dc7ab921c29f502e2e553d89d69aee169a9","amp;dn":"Golden+Dawn+-+Return+to+Provenance+%282012%29+%5Bmp3%40320%5D","amp;tr":["udp%3A%2F%2Ftracker.openbittorrent.com%3A80","udp%3A%2F%2Fopen.demonii.com%3A1337","udp%3A%2F%2Ftracker.coppersurfer.tk%3A6969","udp%3A%2F%2Fexodus.desync.com%3A6969"],"infoHash":"a4bd8dc7ab921c29f502e2e553d89d69aee169a9","infoHashBuffer":{"type":"Buffer","data":[164,189,141,199,171,146,28,41,245,2,226,229,83,216,157,105,174,225,105,169]},"announce":[],"urlList":[]}}