{"title":"Supernatural S07E01 PROPER HDTV XviD-2HD [eztv]","uid":6697724,"size":366727714,"categoryP":"video","categoryS":"tv_shows","magnet":"?xt=urn:btih:b0e2dc2aff18821ba74ec6b9ab3bc2d7114ccadd&amp;dn=Supernatural+S07E01+PROPER+HDTV+XviD-2HD+%5Beztv%5D&amp;tr=udp%3A%2F%2Ftracker.openbittorrent.com%3A80&amp;tr=udp%3A%2F%2Fopen.demonii.com%3A1337&amp;tr=udp%3A%2F%2Ftracker.coppersurfer.tk%3A6969&amp;tr=udp%3A%2F%2Fexodus.desync.com%3A6969","seeders":1,"leechers":0,"uploader":"eztv","files":1,"time":1316851272,"description":"#EZTV @ EFNet -&gt; To avoid fakes, ALWAYS check that the torrent was added by eztv. &lt;a href=&quot;\nhttp://eztv.it/&quot; rel=&quot;nofollow&quot; target=&quot;_NEW&quot;&gt;\nhttp://eztv.it/&lt;/a&gt;\n\nEpisode: Supernatural S07E01 PROPER HDTV XviD-2HD\nScreenshots: &lt;a href=&quot;\nhttp://www.imgden.com/14563/Supernatural.S07E01.PROPER.HDTV.XviD-2HD.avi.jpg&quot; rel=&quot;nofollow&quot; target=&quot;_NEW&quot;&gt;\nhttp://www.imgden.com/14563/Supernatural.S07E01.PROPER.HDTV.XviD-2HD.avi.jpg&lt;/a&gt;\n\n\nWant to help us out? BitCoin: 1Fw4sRdZYFwULfeE7oQ91GLYKy8j5EcuFW","torrent":{"xt":"urn:btih:b0e2dc2aff18821ba74ec6b9ab3bc2d7114ccadd","amp;dn":"Supernatural+S07E01+PROPER+HDTV+XviD-2HD+%5Beztv%5D","amp;tr":["udp%3A%2F%2Ftracker.openbittorrent.com%3A80","udp%3A%2F%2Fopen.demonii.com%3A1337","udp%3A%2F%2Ftracker.coppersurfer.tk%3A6969","udp%3A%2F%2Fexodus.desync.com%3A6969"],"infoHash":"b0e2dc2aff18821ba74ec6b9ab3bc2d7114ccadd","infoHashBuffer":{"type":"Buffer","data":[176,226,220,42,255,24,130,27,167,78,198,185,171,59,194,215,17,76,202,221]},"announce":[],"urlList":[]}}