{"title":"[DoubleTeamedTeens.com] Leah","uid":6755328,"size":606009196,"categoryP":"porn","categoryS":"movie_clips","magnet":"?xt=urn:btih:b2d0d9f1f09c7a4a3b1b12f72bd6107d93af92db&amp;dn=%5BDoubleTeamedTeens.com%5D+Leah&amp;tr=udp%3A%2F%2Ftracker.openbittorrent.com%3A80&amp;tr=udp%3A%2F%2Fopen.demonii.com%3A1337&amp;tr=udp%3A%2F%2Ftracker.coppersurfer.tk%3A6969&amp;tr=udp%3A%2F%2Fexodus.desync.com%3A6969","seeders":0,"leechers":1,"uploader":"chkm8te","files":3,"time":1319019265,"description":"Screens: &lt;a href=&quot;\nhttp://4ufrom.me/viewer.php?file=d7ay2vvgjaqkhqorm0ua.jpg&quot; rel=&quot;nofollow&quot; target=&quot;_NEW&quot;&gt;\nhttp://4ufrom.me/viewer.php?file=d7ay2vvgjaqkhqorm0ua.jpg&lt;/a&gt;\n &lt;a href=&quot;\nhttp://4ufrom.me/viewer.php?file=ke2xmrm75rza9kf9c4d0.jpg&quot; rel=&quot;nofollow&quot; target=&quot;_NEW&quot;&gt;\nhttp://4ufrom.me/viewer.php?file=ke2xmrm75rza9kf9c4d0.jpg&lt;/a&gt;","torrent":{"xt":"urn:btih:b2d0d9f1f09c7a4a3b1b12f72bd6107d93af92db","amp;dn":"%5BDoubleTeamedTeens.com%5D+Leah","amp;tr":["udp%3A%2F%2Ftracker.openbittorrent.com%3A80","udp%3A%2F%2Fopen.demonii.com%3A1337","udp%3A%2F%2Ftracker.coppersurfer.tk%3A6969","udp%3A%2F%2Fexodus.desync.com%3A6969"],"infoHash":"b2d0d9f1f09c7a4a3b1b12f72bd6107d93af92db","infoHashBuffer":{"type":"Buffer","data":[178,208,217,241,240,156,122,74,59,27,18,247,43,214,16,125,147,175,146,219]},"announce":[],"urlList":[]}}