{"title":"(Blues) Rev. Gary Davis - Live At Gerde's Folk City","uid":6108674,"size":394821795,"categoryP":"audio","categoryS":"music","magnet":"?xt=urn:btih:cbaf6870afa4d0d12cf8bd6814bd44c1c8d6b441&amp;dn=%28Blues%29+Rev.+Gary+Davis+-+Live+At+Gerde%5C%27s+Folk+City&amp;tr=udp%3A%2F%2Ftracker.openbittorrent.com%3A80&amp;tr=udp%3A%2F%2Fopen.demonii.com%3A1337&amp;tr=udp%3A%2F%2Ftracker.coppersurfer.tk%3A6969&amp;tr=udp%3A%2F%2Fexodus.desync.com%3A6969","seeders":0,"leechers":1,"uploader":"nightissuchproximity","files":-1,"time":1295222743,"description":"Styles: Acoustic Blues, Blues Gospel, Folk-Blues\nReleased: 2009\nLabel: Stefan Grossman\nFile: mp3@320K/s\nSize: 122.7 + 112.7 + 141.1 MB\nTime: 53:35 + 49:15 + 61:37\nArt: front\n\n\n\nDisc 1\n1. You've Got to Move - 5:15\n2. Intro to Come Down and See Me Sometime - 2:04\n3. Come Down and See Me Sometime - 7:54\n4. Wouldn't Say Quit - 5:16\n5. Oh Lord - 6:50\n6. Announcing Guitar Lessons - 1:00\n7. People That Use to See Can't See No More - 3:54\n8. There's Destruction in This Land - 7:55\n9. Intro to Soon My Work Will All Be Done - 3:35\n10. Soon My Work Will All Be Done - 3:22\n11. Intro to Oh Glory, How Happy I Am - 0:52\n12. Oh Glory, How Happy I Am - 5:35\n\nDisc 2\n1. I Want to Be Saved - 4:14\n2. Just a Closer Walk With Thee - 3:46\n3. Death Don't Have No Mercy - 5:18\n4. Lord I Won't Go Back to Sin - 3:55\n5. Candyman - 3:14\n6. Buck Dance - 5:19\n7. Samson and Delilah - 3:58\n8. Working on the Building - 4:47\n9. I'll Fly Away - 4:03\n10. Sun Goin' Down - 4:11\n11. Fox Chase - 6:26\n\nDisc 3\n1. God's Gonna Separate - 2:51\n2. Lord Search My Heart - 3:43\n3. Jesus Met the Woman at the Well - 5:36\n4. Say No to the Devil - 6:07\n5. I am a Pilgrim - 6:09\n6. All Night Long - 5:40\n7. Trying to Get to Heaven - 4:17\n8. Thank You Jesus - 3:07\n9. Twelve Sticks - 3:02\n10. Intro to Tesse - 2:43\n11. Tesse - 3:02\n12. Lord They Tell Me - 6:23\n13. Right or Wrong - 8:51\n\n\nIs there anyone else out there (or is it\njust me) that thinks Hilary Clinton is sexy as fuck?\n\n\n\n","torrent":{"xt":"urn:btih:cbaf6870afa4d0d12cf8bd6814bd44c1c8d6b441","amp;dn":"%28Blues%29+Rev.+Gary+Davis+-+Live+At+Gerde%5C%27s+Folk+City","amp;tr":["udp%3A%2F%2Ftracker.openbittorrent.com%3A80","udp%3A%2F%2Fopen.demonii.com%3A1337","udp%3A%2F%2Ftracker.coppersurfer.tk%3A6969","udp%3A%2F%2Fexodus.desync.com%3A6969"],"infoHash":"cbaf6870afa4d0d12cf8bd6814bd44c1c8d6b441","infoHashBuffer":{"type":"Buffer","data":[203,175,104,112,175,164,208,209,44,248,189,104,20,189,68,193,200,214,180,65]},"announce":[],"urlList":[]}}