{"title":"60 Sexy Girls Selfies Photos [Mixed Res][Set 52]","uid":15254014,"size":8995795,"categoryP":"other","categoryS":"pictures","magnet":"?xt=urn:btih:ce084f1e4bbe4ec4eca18ebb48929798bc628273&amp;dn=60+Sexy+Girls+Selfies+Photos+%5BMixed+Res%5D%5BSet+52%5D&amp;tr=udp%3A%2F%2Ftracker.leechers-paradise.org%3A6969&amp;tr=udp%3A%2F%2Fzer0day.ch%3A1337&amp;tr=udp%3A%2F%2Fopen.demonii.com%3A1337&amp;tr=udp%3A%2F%2Ftracker.coppersurfer.tk%3A6969&amp;tr=udp%3A%2F%2Fexodus.desync.com%3A6969","seeders":1,"leechers":1,"uploader":"nico1899","files":65,"time":1468092885,"description":"60 Sexy Girls Selfies Photos [Mixed Res][Set 52]\r\n\r\n60 JPG | Mixed Res | 8.57 Mb\r\n\r\n******************************PREVIEWS******************************\r\n \nhttp://picrelated.com/image/8k4xh\r\n \nhttp://picrelated.com/image/8kFdK\r\n \nhttp://picrelated.com/image/8kT0y\r\n \nhttp://picrelated.com/image/8kKm3\r\n \nhttp://imgvortex.com/image/EX9P9\r\n\r\n********************************************************************","torrent":{"xt":"urn:btih:ce084f1e4bbe4ec4eca18ebb48929798bc628273","amp;dn":"60+Sexy+Girls+Selfies+Photos+%5BMixed+Res%5D%5BSet+52%5D","amp;tr":["udp%3A%2F%2Ftracker.leechers-paradise.org%3A6969","udp%3A%2F%2Fzer0day.ch%3A1337","udp%3A%2F%2Fopen.demonii.com%3A1337","udp%3A%2F%2Ftracker.coppersurfer.tk%3A6969","udp%3A%2F%2Fexodus.desync.com%3A6969"],"infoHash":"ce084f1e4bbe4ec4eca18ebb48929798bc628273","infoHashBuffer":{"type":"Buffer","data":[206,8,79,30,75,190,78,196,236,161,142,187,72,146,151,152,188,98,130,115]},"announce":[],"urlList":[]}}