{"title":"A.Young.Doctors.Notebook.S02E02.720p.HDTV.x264-iOM","uid":9264640,"size":367488880,"categoryP":"video","categoryS":"hd___tv_shows","magnet":"?xt=urn:btih:e0a477e5e696899f9c3c8599061cf5f9421675be&amp;dn=A.Young.Doctors.Notebook.S02E02.720p.HDTV.x264-iOM&amp;tr=udp%3A%2F%2Ftracker.openbittorrent.com%3A80&amp;tr=udp%3A%2F%2Fopen.demonii.com%3A1337&amp;tr=udp%3A%2F%2Ftracker.coppersurfer.tk%3A6969&amp;tr=udp%3A%2F%2Fexodus.desync.com%3A6969","seeders":0,"leechers":1,"uploader":"sceneline","files":12,"time":1385680607,"description":"Please Seed back to make the speed Faster!!\nand use comment \n ............ NFO .............\n-","torrent":{"xt":"urn:btih:e0a477e5e696899f9c3c8599061cf5f9421675be","amp;dn":"A.Young.Doctors.Notebook.S02E02.720p.HDTV.x264-iOM","amp;tr":["udp%3A%2F%2Ftracker.openbittorrent.com%3A80","udp%3A%2F%2Fopen.demonii.com%3A1337","udp%3A%2F%2Ftracker.coppersurfer.tk%3A6969","udp%3A%2F%2Fexodus.desync.com%3A6969"],"infoHash":"e0a477e5e696899f9c3c8599061cf5f9421675be","infoHashBuffer":{"type":"Buffer","data":[224,164,119,229,230,150,137,159,156,60,133,153,6,28,245,249,66,22,117,190]},"announce":[],"urlList":[]}}