{"title":"PRRPM 04 Go For the Green (deka).avi","uid":4790525,"size":243220480,"categoryP":"video","categoryS":"tv_shows","magnet":"?xt=urn:btih:e13a77ee5ff4c1432562f43bf317980db7db810d&amp;dn=PRRPM+04+Go+For+the+Green+%28deka%29.avi&amp;tr=udp%3A%2F%2Ftracker.openbittorrent.com%3A80&amp;tr=udp%3A%2F%2Fopen.demonii.com%3A1337&amp;tr=udp%3A%2F%2Ftracker.coppersurfer.tk%3A6969&amp;tr=udp%3A%2F%2Fexodus.desync.com%3A6969","seeders":1,"leechers":1,"uploader":"burgundyranger","files":1,"time":1237701091,"description":"Episode 4 of Power Rangers RPM, encoded by dekabroken","torrent":{"xt":"urn:btih:e13a77ee5ff4c1432562f43bf317980db7db810d","amp;dn":"PRRPM+04+Go+For+the+Green+%28deka%29.avi","amp;tr":["udp%3A%2F%2Ftracker.openbittorrent.com%3A80","udp%3A%2F%2Fopen.demonii.com%3A1337","udp%3A%2F%2Ftracker.coppersurfer.tk%3A6969","udp%3A%2F%2Fexodus.desync.com%3A6969"],"infoHash":"e13a77ee5ff4c1432562f43bf317980db7db810d","infoHashBuffer":{"type":"Buffer","data":[225,58,119,238,95,244,193,67,37,98,244,59,243,23,152,13,183,219,129,13]},"announce":[],"urlList":[]}}