{"title":"Naruto_Clash_Of_Ninja_Revolution_PAL_Wii-WiiERD ","uid":4094715,"size":4630244944,"categoryP":"games","categoryS":"wii","magnet":"?xt=urn:btih:e68cb239fb46e7cc662010a57491775db3940ea9&amp;dn=Naruto_Clash_Of_Ninja_Revolution_PAL_Wii-WiiERD+&amp;tr=udp%3A%2F%2Ftracker.openbittorrent.com%3A80&amp;tr=udp%3A%2F%2Fopen.demonii.com%3A1337&amp;tr=udp%3A%2F%2Ftracker.coppersurfer.tk%3A6969&amp;tr=udp%3A%2F%2Fexodus.desync.com%3A6969","seeders":1,"leechers":1,"uploader":"superdescargas","files":95,"time":1206248518,"description":"The Clash of Ninja games havenÂ´t been great, and Revolution isnÂ´t much more than a thin coat of paint on the same old game.","torrent":{"xt":"urn:btih:e68cb239fb46e7cc662010a57491775db3940ea9","amp;dn":"Naruto_Clash_Of_Ninja_Revolution_PAL_Wii-WiiERD+","amp;tr":["udp%3A%2F%2Ftracker.openbittorrent.com%3A80","udp%3A%2F%2Fopen.demonii.com%3A1337","udp%3A%2F%2Ftracker.coppersurfer.tk%3A6969","udp%3A%2F%2Fexodus.desync.com%3A6969"],"infoHash":"e68cb239fb46e7cc662010a57491775db3940ea9","infoHashBuffer":{"type":"Buffer","data":[230,140,178,57,251,70,231,204,102,32,16,165,116,145,119,93,179,148,14,169]},"announce":[],"urlList":[]}}