{"title":"MonstersOfCock - Lela Star (Lela Star patiently waits for a crea","uid":13254141,"size":298739172,"categoryP":"porn","categoryS":"movie_clips","magnet":"?xt=urn:btih:f0a4a9f03d1ae448f2feb26c629b1d148a1e8ee4&amp;dn=MonstersOfCock+-+Lela+Star+%28Lela+Star+patiently+waits+for+a+crea&amp;tr=udp%3A%2F%2Ftracker.leechers-paradise.org%3A6969&amp;tr=udp%3A%2F%2Fzer0day.ch%3A1337&amp;tr=udp%3A%2F%2Fopen.demonii.com%3A1337&amp;tr=udp%3A%2F%2Ftracker.coppersurfer.tk%3A6969&amp;tr=udp%3A%2F%2Fexodus.desync.com%3A6969","seeders":1,"leechers":0,"uploader":"xxxlavalxxx","files":2,"time":1453206524,"description":"Lela Star sat patiently waiting for her Monster Cock to get home from a long day at work. She was hot and horny. This Milf has ass for days and Stallion has a big dick to satisfy her horniness. The second he walks trough the doors, Lela pulled his pants down and deep throated that dick. Slobbering all over it. Making it wet so it can slide deep in her throbbing pussy. Stallion beat that pussy up! From all angles. Cumming deep inside her pussy.\r\nTags:Big Tits, Big Ass, Big Dick, Blowjob, Creampie, Handjob, Hardcore, Interracial, Pornstar, White Girl\r\n \nhttp://imgdone.com/viewer.php?file=71580750098759410620.jpg\r\n \nhttp://imgdone.com/viewer.php?file=74488025038925918974.jpg","torrent":{"xt":"urn:btih:f0a4a9f03d1ae448f2feb26c629b1d148a1e8ee4","amp;dn":"MonstersOfCock+-+Lela+Star+%28Lela+Star+patiently+waits+for+a+crea","amp;tr":["udp%3A%2F%2Ftracker.leechers-paradise.org%3A6969","udp%3A%2F%2Fzer0day.ch%3A1337","udp%3A%2F%2Fopen.demonii.com%3A1337","udp%3A%2F%2Ftracker.coppersurfer.tk%3A6969","udp%3A%2F%2Fexodus.desync.com%3A6969"],"infoHash":"f0a4a9f03d1ae448f2feb26c629b1d148a1e8ee4","infoHashBuffer":{"type":"Buffer","data":[240,164,169,240,61,26,228,72,242,254,178,108,98,155,29,20,138,30,142,228]},"announce":[],"urlList":[]}}