{"title":"VA_-_Clubfanatix_297_In_Music_We_Trust-2012-VANiLLA","uid":7752446,"size":164879556,"categoryP":"audio","categoryS":"music","magnet":"?xt=urn:btih:fb56255b3444a47605af6f4fdc7213126264a510&amp;dn=VA_-_Clubfanatix_297_In_Music_We_Trust-2012-VANiLLA&amp;tr=udp%3A%2F%2Ftracker.openbittorrent.com%3A80&amp;tr=udp%3A%2F%2Fopen.demonii.com%3A1337&amp;tr=udp%3A%2F%2Ftracker.coppersurfer.tk%3A6969&amp;tr=udp%3A%2F%2Fexodus.desync.com%3A6969","seeders":1,"leechers":0,"uploader":null,"files":23,"time":1351001257,"description":"########################################################\n   ________      __    ____                  __  _      \n  / ____/ /_  __/ /_  / __/___ _____  ____ _/ /_(_)  __ \n / /   / / / / / __ / /_/ __ `/ __ / __ `/ __/ / |/_/ \n/ /___/ / /_/ / /_/ / __/ /_/ / / / / /_/ / /_/ /&gt;  &lt;   \n____/_/__,_/_.___/_/  __,_/_/ /_/__,_/__/_/_/|_|   \n\n########################################################\n The Beatz. The Melody. The Baze.                       \n\t\t     The Bootleg That Rocks The Plaze   \n########################################################\n\nCollector   : D0M0KUN\nGenre       : Hands Up, Dance, Trance, House &amp; Hardstyle\nDate        : 22-10-2012\nYear        : 2012\nEncoder     : LAME\nQuality     : Various\nTracks      : 20\nPlaytime    : 1:10:06\nSize        : 157MB\n\n########################################################\n Tracklist:\n########################################################\n 01. 01-manuel_lauren_-_dj_aflame_(cc.k_radio_mix)\n 02. 02-clubraiders_-_cant_stop_my_love_(alexkea_feat_ra\n 03. 03-dj_gollum_vs_empyre_one_-_the_bad_touch_(empyre_\n 04. 04-ricardas_-_break_the_wall_(basador_radio_mix)\n 05. 05-vanilla_kiss_-_home_alone_(kinky_boyz_remix_cut)\n 06. 06-tao_hypah_-_play_the_girl_(jammin_the_shit_radio\n 07. 07-rihanna_-_diamonds_(n-vision_bootleg_radio_edit)\n 08. 08-katy_perry_-_california_gurls_(redtzer_bootleg_e\n 09. 09-dj_doddo_vs_glaukor_ft_morgana_-_hi_(radio_edit)\n 10. 10-shaun_baker_feat_maloy_-_theres_nothing_i_wont_d\n 11. 11-kindervater_-_shooting_stars_(radio_edit)\n 12. 12-brilliant_feat_drew_darcy_-_londons_on_fire_(voc\n 13. 13-j3n5on_-_wup_wup_(original_radio_edit)\n 14. 14-hornyshakerz_feat_de-vision_-_time_to_be_alive_2\n 15. 15-clubhunter_-_we_can_fly_(turbotronic_radio_edit)\n 16. 16-taio_cruz_-_fast_car_(davis_redfield_remix_cut)\n 17. 17-cassey_doreen_&amp;_loona_-_tell_it_to_my_heart_(loo\n 18. 18-b-twinz_-_shout_(original_edit)\n 19. 19-psy_-_gangnam_style_(jml_bootleg_cut)\n 20. 20-jaydee_-_state_of_mind_(original_edit)\n########################################################","torrent":{"xt":"urn:btih:fb56255b3444a47605af6f4fdc7213126264a510","amp;dn":"VA_-_Clubfanatix_297_In_Music_We_Trust-2012-VANiLLA","amp;tr":["udp%3A%2F%2Ftracker.openbittorrent.com%3A80","udp%3A%2F%2Fopen.demonii.com%3A1337","udp%3A%2F%2Ftracker.coppersurfer.tk%3A6969","udp%3A%2F%2Fexodus.desync.com%3A6969"],"infoHash":"fb56255b3444a47605af6f4fdc7213126264a510","infoHashBuffer":{"type":"Buffer","data":[251,86,37,91,52,68,164,118,5,175,111,79,220,114,19,18,98,100,165,16]},"announce":[],"urlList":[]}}